neo4j_runway/__init__.py
neo4j_runway/code_generation/__init__.py
neo4j_runway/code_generation/base.py
neo4j_runway/code_generation/cypher/__init__.py
neo4j_runway/code_generation/cypher/base.py
neo4j_runway/code_generation/cypher/constraints.py
neo4j_runway/code_generation/cypher/indexes.py
neo4j_runway/code_generation/cypher/misc.py
neo4j_runway/code_generation/load_csv/load_csv_generator.py
neo4j_runway/code_generation/pyingest/pyingest_generator.py
neo4j_runway/code_generation/standard/standard_cypher_generator.py
neo4j_runway/database/__init__.py
neo4j_runway/database/base.py
neo4j_runway/database/neo4j/__init__.py
neo4j_runway/database/neo4j/neo4j_graph.py
neo4j_runway/discovery/__init__.py
neo4j_runway/discovery/discovery.py
neo4j_runway/discovery/discovery_content.py
neo4j_runway/exceptions.py
neo4j_runway/graph_eda/__init__.py
neo4j_runway/graph_eda/cache.py
neo4j_runway/graph_eda/graph_eda.py
neo4j_runway/graph_eda/queries.py
neo4j_runway/graph_eda/report/formatters.py
neo4j_runway/graph_eda/report/template.py
neo4j_runway/ingestion/__init__.py
neo4j_runway/ingestion/pyingest.py
neo4j_runway/inputs/__init__.py
neo4j_runway/inputs/user_input.py
neo4j_runway/llm/base.py
neo4j_runway/llm/context.py
neo4j_runway/llm/openai/__init__.py
neo4j_runway/llm/openai/azure/data_modeling.py
neo4j_runway/llm/openai/azure/discovery.py
neo4j_runway/llm/openai/data_modeling.py
neo4j_runway/llm/openai/discovery.py
neo4j_runway/llm/retry.py
neo4j_runway/modeler/__init__.py
neo4j_runway/modeler/modeler.py
neo4j_runway/models/__init__.py
neo4j_runway/models/arrows/__init__.py
neo4j_runway/models/arrows/data_model.py
neo4j_runway/models/arrows/node.py
neo4j_runway/models/arrows/relationship.py
neo4j_runway/models/core/__init__.py
neo4j_runway/models/core/data_model.py
neo4j_runway/models/core/node.py
neo4j_runway/models/core/property.py
neo4j_runway/models/core/relationship.py
neo4j_runway/models/core/visualization.py
neo4j_runway/models/solutions_workbench/__init__.py
neo4j_runway-0.14.0.dist-info/LICENSE
neo4j_runway-0.14.0.dist-info/METADATA
neo4j_runway-0.14.0.dist-info/WHEEL
neo4j_runway-0.14.0.dist-info/RECORD
