Metadata-Version: 2.1
Name: neo4j-runway
Version: 0.14.0
Summary: A Python library that contains tools for data discovery, data model generation and ingestion for the Neo4j graph database.
License: Apache License, Version 2.0
Keywords: graph,neo4j,data model
Author: Alex Gilmore
Requires-Python: >=3.10,<4.0
Classifier: Development Status :: 4 - Beta
Classifier: Intended Audience :: Developers
Classifier: License :: OSI Approved :: Apache Software License
Classifier: License :: Other/Proprietary License
Classifier: Operating System :: OS Independent
Classifier: Programming Language :: Python
Classifier: Programming Language :: Python :: 3
Classifier: Programming Language :: Python :: 3.10
Classifier: Programming Language :: Python :: 3.11
Classifier: Programming Language :: Python :: 3.12
Classifier: Topic :: Database
Classifier: Topic :: Software Development :: Libraries :: Python Modules
Requires-Dist: graphviz (>=0.20.1,<0.21.0)
Requires-Dist: instructor (==1.5.2)
Requires-Dist: ipython (>=8.24.0,<9.0.0)
Requires-Dist: neo4j (>=5.19.0,<6.0.0)
Requires-Dist: nest_asyncio (>=1.6.0,<2.0.0)
Requires-Dist: numpy (>=1.26.3,<2.0.0)
Requires-Dist: openai (>=1.12.0,<2.0.0)
Requires-Dist: pandas (>=2.0.3,<3.0.0)
Requires-Dist: pydantic (>=2.6.1,<3.0.0)
Requires-Dist: pyyaml (>=6.0.1,<7.0.0)
Requires-Dist: regex (>=2024,<2025)
Requires-Dist: tabulate (>=0.9.0,<0.10.0)
